README.rst
setup.py
scikit2pmml/__init__.py
scikit2pmml.egg-info/PKG-INFO
scikit2pmml.egg-info/SOURCES.txt
scikit2pmml.egg-info/dependency_links.txt
scikit2pmml.egg-info/requires.txt
scikit2pmml.egg-info/top_level.txt
scikit2pmml/models/__init__.py
scikit2pmml/models/ensemble.py
scikit2pmml/models/regression.py
scikit2pmml/models/tree.py